[
  {
    "companyName": "EG Allied Pvt. Ltd.",
    "externalUrl": "http:\/\/www.linkedin.com\/jobs\/view\/3981404449",
    "description": ""
  },
  {
    "companyName": "Velotio Technologies",
    "externalUrl": "http:\/\/www.linkedin.com\/jobs\/view\/3981942828",
    "description": ""
  },
  {
    "companyName": "Senovo IT Ltd",
    "externalUrl": "http:\/\/www.linkedin.com\/jobs\/view\/3982733812",
    "description": ""
  },
  {
    "companyName": "Dashwave",
    "externalUrl": "http:\/\/www.linkedin.com\/jobs\/view\/3982859577",
    "description": ""
  },
  {
    "companyName": "Nextgen Technologies Inc",
    "externalUrl": "http:\/\/www.linkedin.com\/jobs\/view\/3985593454",
    "description": ""
  }
]